brs_libs/__init__.py
brs_libs/__main__.py
brs_libs/inchikeyMIRIAM.py
brs_libs/rpCache.py
brs_libs/rpSBML.py
brs_libs-0.3.0.dist-info/LICENSE
brs_libs-0.3.0.dist-info/METADATA
brs_libs-0.3.0.dist-info/WHEEL
brs_libs-0.3.0.dist-info/top_level.txt
brs_libs-0.3.0.dist-info/RECORD
