Metadata-Version: 2.1
Name: brs-libs
Version: 0.3.0
Summary: 'libraries for rptools'
Home-page: https://github.com/brsynth/brs_libs
Author: 'melchior du lac, joan hérisson'
Author-email: joan.herisson@univ-evry.fr
License: MIT
Platform: UNKNOWN
Classifier: Programming Language :: Python :: 3
Classifier: License :: OSI Approved :: MIT License
Classifier: Operating System :: OS Independent
Requires-Python: >=3.5
Requires-Dist: python-libsbml
Requires-Dist: numpy
Requires-Dist: pandas
Requires-Dist: brs-utils
Requires-Dist: credisdict
Requires-Dist: redis
Requires-Dist: requests
Requires-Dist: colored
